automodel.py
setup.cfg
setup.py
MiniServer/__init__.py
MiniServer/adapter.py
MiniServer/file.py
MiniServer/modelagem.py
MiniServer/pdb.py
MiniServer/sequence.py
MiniServer/server.py
automodel.egg-info/PKG-INFO
automodel.egg-info/SOURCES.txt
automodel.egg-info/dependency_links.txt
automodel.egg-info/requires.txt
automodel.egg-info/top_level.txt
automodelexception/__init__.py
automodelexception/automodel_error.py
manual/__init__.py
model/AutoModelMode.py
model/__init__.py
modellingfile/AlignFile.py
modellingfile/AlignFile_test.py
modellingfile/FastaFile.py
modellingfile/PDB2.py
modellingfile/PirSequence.py
modellingfile/PirSequence_test.py
modellingfile/__init__.py
modellingfile/file.py
modellingfile/fixpdb.py
modellingfile/leitorprf.py
modellingfile/pdb_file.py
modellingfile/pdbfile.py
modellingfile/pdbfile_test.py
modellingfile/residues.py
modellingfile/residues_test.py
modellingfile/seq.py
modellingfiles/__init__.py
modellingstep/AlignStep.py
modellingstep/EvaluateAfterLoopRefinamentStep.py
modellingstep/EvaluateProcheckStep.py
modellingstep/EvaluateStep.py
modellingstep/FindTemplatesStep.py
modellingstep/LoopModelStep.py
modellingstep/ModelStep.py
modellingstep/ModellingStep.py
modellingstep/PrepareBeforeStartModelling.py
modellingstep/__init__.py
network/Clientold.py
network/__init__.py
network/client.py
network/clientX.py
options/Options.py
options/Options_test.py
options/Prefs.py
options/Prefs_test.py
options/__init__.py
pdb/compare.py
tests/server_test.py
window/AboutAutoModel.py
window/AlignmentEditorWindow.py
window/AlterarCadeiasEHeteroatomos.py
window/ImageViewerWindow.py
window/MiniFrame1.py
window/SelectAutoModelMode.py
window/SelectAutoModelTypeWindow.py
window/SelectTemplate_Window.py
window/TextEditorWindow.py
window/__init__.py
window/automatic_align_window.py
window/automatic_modeling_window.py
window/change_het_window.py
window/change_het_window_test.py
window/loop_window.py
window/main_window.py
window/main_window_mini.py
window/sequence_window.py
window/show_window_send_serial.py
wintools/__init__.py
wintools/wintools.py