Metadata-Version: 1.0
Name: automodel
Version: 0.5.9
Summary: Client of service for structure protein prediction
Home-page: UNKNOWN
Author: João Luiz de Almeida Filho, Jorge Hernandez Fernandez
Author-email: joaoluiz.af@gmail.com
License: UNKNOWN
Keywords: protein modeling modeller automodel
Platform: UNKNOWN
